regreplace/__init__.py
regreplace/main.py
regreplace-0.1.5.dist-info/METADATA
regreplace-0.1.5.dist-info/WHEEL
regreplace-0.1.5.dist-info/RECORD
