Metadata-Version: 2.1
Name: regreplace
Version: 0.1.5
Summary: Replace named regex group by a given string
Author: Gwang-Jin Kim
Author-email: gwang.jin.kim.phd@gmail.com
Requires-Python: >=3.7,<4.0
Classifier: Programming Language :: Python :: 3
Classifier: Programming Language :: Python :: 3.7
Classifier: Programming Language :: Python :: 3.8
Classifier: Programming Language :: Python :: 3.9
Classifier: Programming Language :: Python :: 3.10
Classifier: Programming Language :: Python :: 3.11
Classifier: Programming Language :: Python :: 3.12
